{"@type": "dcat:Dataset", "accessLevel": "public", "accrualPeriodicity": "R/P1M", "bureauCode": ["006:07"], "contactPoint": {"@type": "vcard:Contact", "fn": "Phil Thompson", "hasEmail": "mailto:philip.w.thompson@census.gov"}, "dataQuality": true, "describedBy": "http://www.census.gov/construction/cpi/definitions/", "description": "The Construction Price Indexes provide price indexes for single-family houses sold and for single-family houses under construction. The houses sold index incorporates the value of the land and is available quarterly at the national level and annually by region. The indexes for houses under construction are available monthly at the national level. The indexes are based on data funded by HUD and collected in the Survey of Construction (SOC).", "distribution": [{"@type": "dcat:Distribution", "downloadURL": "http://www.census.gov/construction/cpi/", "mediaType": "text/html", "title": "Web Page"}], "identifier": "DOC-5602", "issued": "1963-01-01", "keyword": ["Constant", "Deflator", "Fisher", "Ideal", "Index", "Laspeyres", "Output", "Paasche", "Quality", "absorption", "apartment", "authorization", "authorized", "build", "building", "built", "characteristic", "completed", "completion", "construction", "contract", "contractor", "cost", "development", "dwelling", "economic", "existing", "expenditures", "family", "financing", "finished", "floor", "home", "house", "houses", "housing", "hud", "index", "indicator", "issue", "issuing", "living", "manufactured", "market", "metropolitan", "microdata", "month", "multifamily", "multiple", "new", "nonresidential", "occupancy", "occupants", "occupied", "office", "one-unit", "owner", "permanent", "permit", "permits", "price", "private", "privately-owned", "public", "quarters", "rebuilt", "region", "regional", "rent", "rental", "residential", "rural", "sale", "sectional", "single", "single-family", "site-built", "size", "sold", "speculative", "spending", "stage", "started", "starts", "structure", "timeshare", "u s", "under", "unit", "units", "urban", "vacancy", "valuation", "zoning"], "license": "http://www.usa.gov/publicdomain/label/1.0/", "modified": "2016-06-23", "programCode": ["006:007"], "publisher": {"@type": "org:Organization", "name": "US Census Bureau, Department of Commerce"}, "references": ["http://www.census.gov/construction/cpi/how_the_data_are_collected/"], "spatial": "United States", "title": "Construction Price Indexes"}